refitt/__init__.py
refitt/apps/__init__.py
refitt/apps/refitt/__init__.py
refitt/apps/refitt/api.py
refitt/apps/refitt/auth.py
refitt/apps/refitt/config.py
refitt/apps/refitt/epoch.py
refitt/apps/refitt/login.py
refitt/apps/refitt/object.py
refitt/apps/refitt/whoami.py
refitt/apps/refitt/database/__init__.py
refitt/apps/refitt/database/check.py
refitt/apps/refitt/database/init.py
refitt/apps/refitt/database/query.py
refitt/apps/refitt/forecast/__init__.py
refitt/apps/refitt/forecast/create.py
refitt/apps/refitt/forecast/publish.py
refitt/apps/refitt/notify/__init__.py
refitt/apps/refitt/notify/mail.py
refitt/apps/refitt/notify/slack.py
refitt/apps/refitt/recommendation/__init__.py
refitt/apps/refitt/recommendation/publish.py
refitt/apps/refitt/service/__init__.py
refitt/apps/refitt/service/api.py
refitt/apps/refitt/service/stream.py
refitt/apps/refitt/service/test.py
refitt/apps/refitt/service/tns.py
refitt/apps/refittctl/__init__.py
refitt/apps/refittd/__init__.py
refitt/assets/__init__.py
refitt/assets/cluster/pipeline.pbs-torque.bash
refitt/assets/config/refitt.toml
refitt/assets/database/core/file_type.json
refitt/assets/database/core/level.json
refitt/assets/database/core/model_type.json
refitt/assets/database/core/object_type.json
refitt/assets/database/core/observation_type.json
refitt/assets/database/core/source.json
refitt/assets/database/core/source_type.json
refitt/assets/database/core/topic.json
refitt/assets/database/core/user.json
refitt/assets/database/test/alert.json
refitt/assets/database/test/client.json
refitt/assets/database/test/epoch.json
refitt/assets/database/test/facility.json
refitt/assets/database/test/facility_map.json
refitt/assets/database/test/file.json
refitt/assets/database/test/file_type.json
refitt/assets/database/test/level.json
refitt/assets/database/test/model.json
refitt/assets/database/test/model_type.json
refitt/assets/database/test/object.json
refitt/assets/database/test/object_type.json
refitt-0.24.0.dist-info/LICENSE
refitt-0.24.0.dist-info/METADATA
refitt-0.24.0.dist-info/WHEEL
refitt-0.24.0.dist-info/entry_points.txt
refitt-0.24.0.dist-info/top_level.txt
refitt-0.24.0.dist-info/RECORD
