Metadata-Version: 2.1
Name: refitt
Version: 0.24.0
Summary: The Recommender Engine for Intelligent Transient Tracking.
Home-page: https://github.com/refitt/refitt
Author: Geoffrey Lentner
Author-email: glentner@purdue.edu
License: Apache License 2.0
Keywords: astronomy science machine-learning recommendation service
Classifier: Development Status :: 4 - Beta
Classifier: Topic :: Scientific/Engineering :: Astronomy
Classifier: Programming Language :: Python :: 3
Classifier: Programming Language :: Python :: 3.8
Classifier: Programming Language :: Python :: 3.9
Classifier: Programming Language :: Python :: 3.10
Classifier: Operating System :: POSIX :: Linux
License-File: LICENSE
Requires-Dist: numpy
Requires-Dist: scipy
Requires-Dist: pandas
Requires-Dist: h5py
Requires-Dist: tables
Requires-Dist: pyarrow (>=3.0.0)
Requires-Dist: sqlalchemy
Requires-Dist: psycopg2
Requires-Dist: flask
Requires-Dist: gunicorn
Requires-Dist: requests
Requires-Dist: cryptography (>=3.2.1)
Requires-Dist: cmdkit (>=2.5.1)
Requires-Dist: toml
Requires-Dist: streamkit (>=0.3.2)
Requires-Dist: names-generator (>=0.1.0)
Requires-Dist: astropy (>=4.0.1)
Requires-Dist: antares-client (>=1.0.1)
Requires-Dist: slackclient (>=2.8.0)
Requires-Dist: matplotlib
Requires-Dist: seaborn
Requires-Dist: rich
Requires-Dist: tensorflow (>=2.4.1)
Requires-Dist: parsl
Requires-Dist: astroplan
Requires-Dist: timezonefinder
Requires-Dist: pytz
Requires-Dist: bs4
Requires-Dist: jinja2
